simplemdx/__init__.py
simplemdx/cli.py
simplemdx/declparser.py
simplemdx/parser.py
simplemdx-0.1.10.dist-info/AUTHORS.rst
simplemdx-0.1.10.dist-info/LICENSE
simplemdx-0.1.10.dist-info/METADATA
simplemdx-0.1.10.dist-info/WHEEL
simplemdx-0.1.10.dist-info/entry_points.txt
simplemdx-0.1.10.dist-info/top_level.txt
simplemdx-0.1.10.dist-info/RECORD
