Metadata-Version: 2.1
Name: simplemdx
Version: 0.1.10
Summary: A simple BTS MDX file parser based on BeautifulSoup
Home-page: https://github.com/marnunez/simplemdx
Author: Marcos Alfredo Núñez
Author-email: mnunez@fleni.org.ar
License: GNU GPLv3 Licence
Keywords: simplemdx
Platform: UNKNOWN
Classifier: Development Status :: 2 - Pre-Alpha
Classifier: Intended Audience :: Developers
Classifier: License :: OSI Approved :: GNU General Public License v3 (GPLv3)
Classifier: Natural Language :: English
Classifier: Programming Language :: Python :: 2
Classifier: Programming Language :: Python :: 2.7
Classifier: Programming Language :: Python :: 3
Classifier: Programming Language :: Python :: 3.4
Classifier: Programming Language :: Python :: 3.5
Classifier: Programming Language :: Python :: 3.6
Requires-Dist: Click (>=6.0)
